{"cameraMode":{"drawMode":0,"name":"Shaded","section":"Shading Mode"},"sceneLighting":true,"audioPlay":false,"sceneViewState":{"m_AlwaysRefresh":false,"showFog":true,"showSkybox":true,"showFlares":true,"showImageEffects":true,"showParticleSystems":true,"showVisualEffectGraphs":true,"m_FxEnabled":true},"in2DMode":false,"pivot":{"x":-1.0982379913330079,"y":5.734828472137451,"z":-1.0641593933105469},"rotation":{"x":-0.013992556370794773,"y":0.922121524810791,"z":-0.0334966666996479,"w":-0.38519999384880068},"size":7.789951324462891,"orthographic":false}